byted_overpass_oec_insights_ops_decision/__init__.py
byted_overpass_oec_insights_ops_decision-0.0.1.dist-info/METADATA
byted_overpass_oec_insights_ops_decision-0.0.1.dist-info/WHEEL
byted_overpass_oec_insights_ops_decision-0.0.1.dist-info/top_level.txt
byted_overpass_oec_insights_ops_decision-0.0.1.dist-info/RECORD
